uncertainty_loss/__init__.py
uncertainty_loss/_torch.py
uncertainty_loss-0.1.2.dist-info/LICENSE
uncertainty_loss-0.1.2.dist-info/WHEEL
uncertainty_loss-0.1.2.dist-info/METADATA
uncertainty_loss-0.1.2.dist-info/RECORD
