Metadata-Version: 2.1
Name: uncertainty-loss
Version: 0.1.2
Summary: Uncertainty Loss functions for deep learning
Author: Mike Vaiana
Author-email: mike@ae.studio
Requires-Python: >=3.9,<4.0
Classifier: Programming Language :: Python :: 3
Classifier: Programming Language :: Python :: 3.9
Classifier: Programming Language :: Python :: 3.10
Classifier: Programming Language :: Python :: 3.11
Requires-Dist: numpy (>=1.23.4,<2.0.0)
